{
    "grafika_id": 2675,
    "mime": "image/jpeg",
    "grafika": [],
    "data_wykonania": "/Date(1295391600000)/",
    "dataWykonaniaString": "2011-01-19",
    "grafika_nazwa": "plan",
    "wielkosc": 0,
    "autor_nazwa": "Mleczek Tomasz",
    "jaskinia_id": 0,
    "jaskinia_nazwa": null,
    "typ_grafiki_id": 2,
    "typ_grafiki_nazwa": "plan",
    "nr_inwent": "K.Pr-02.08",
    "region": null,
    "maxWidth": 369,
    "maxHeight": 738,
    "fileUpload": null,
    "Authors": null,
    "GraphicsTypes": null
}