{
    "grafika_id": 759,
    "mime": "image/jpeg",
    "grafika": [],
    "data_wykonania": "/Date(1284242400000)/",
    "dataWykonaniaString": "2010-09-12",
    "grafika_nazwa": "plan",
    "wielkosc": 0,
    "autor_nazwa": "Nowicki Tomasz",
    "jaskinia_id": 0,
    "jaskinia_nazwa": null,
    "typ_grafiki_id": 2,
    "typ_grafiki_nazwa": "plan",
    "nr_inwent": "T.D-18.01",
    "region": null,
    "maxWidth": 2217,
    "maxHeight": 948,
    "fileUpload": null,
    "Authors": null,
    "GraphicsTypes": null
}