{
    "grafika_id": 10116,
    "mime": "image/jpeg",
    "grafika": [],
    "data_wykonania": "/Date(1418511600000)/",
    "dataWykonaniaString": "2014-12-14",
    "grafika_nazwa": "plan",
    "wielkosc": 0,
    "autor_nazwa": "Szelerewicz Mariusz",
    "jaskinia_id": 0,
    "jaskinia_nazwa": null,
    "typ_grafiki_id": 2,
    "typ_grafiki_nazwa": "plan",
    "nr_inwent": "J.Olk.II-01.17",
    "region": null,
    "maxWidth": 443,
    "maxHeight": 614,
    "fileUpload": null,
    "Authors": null,
    "GraphicsTypes": null
}