{
    "grafika_id": 10093,
    "mime": "image/jpeg",
    "grafika": [],
    "data_wykonania": "/Date(1418511600000)/",
    "dataWykonaniaString": "2014-12-14",
    "grafika_nazwa": "przekrój",
    "wielkosc": 0,
    "autor_nazwa": "Szelerewicz Mariusz",
    "jaskinia_id": 0,
    "jaskinia_nazwa": null,
    "typ_grafiki_id": 4,
    "typ_grafiki_nazwa": "przekrój",
    "nr_inwent": "J.Olk.II-01.03",
    "region": null,
    "maxWidth": 748,
    "maxHeight": 953,
    "fileUpload": null,
    "Authors": null,
    "GraphicsTypes": null
}