{
    "grafika_id": 14025,
    "mime": "image/jpeg",
    "grafika": [],
    "data_wykonania": "/Date(1636930800000)/",
    "dataWykonaniaString": "2021-11-15",
    "grafika_nazwa": "otwór",
    "wielkosc": 0,
    "autor_nazwa": "Gubała Wojciech J.",
    "jaskinia_id": 0,
    "jaskinia_nazwa": null,
    "typ_grafiki_id": 1,
    "typ_grafiki_nazwa": "zdjęcie",
    "nr_inwent": "P-05.21",
    "region": null,
    "maxWidth": 900,
    "maxHeight": 1200,
    "fileUpload": null,
    "Authors": null,
    "GraphicsTypes": null
}