{
    "grafika_id": 15119,
    "mime": "image/jpeg",
    "grafika": [],
    "data_wykonania": "/Date(1572822000000)/",
    "dataWykonaniaString": "2019-11-04",
    "grafika_nazwa": "otwór 1 ",
    "wielkosc": 0,
    "autor_nazwa": "Szczygieł Jacek",
    "jaskinia_id": 0,
    "jaskinia_nazwa": null,
    "typ_grafiki_id": 1,
    "typ_grafiki_nazwa": "zdjęcie",
    "nr_inwent": "T.E-11.11",
    "region": null,
    "maxWidth": 683,
    "maxHeight": 910,
    "fileUpload": null,
    "Authors": null,
    "GraphicsTypes": null
}