{
    "grafika_id": 994,
    "mime": "image/jpeg",
    "grafika": [],
    "data_wykonania": "/Date(1285538400000)/",
    "dataWykonaniaString": "2010-09-27",
    "grafika_nazwa": "plan i przekrój",
    "wielkosc": 0,
    "autor_nazwa": "Luty Izabella",
    "jaskinia_id": 0,
    "jaskinia_nazwa": null,
    "typ_grafiki_id": 6,
    "typ_grafiki_nazwa": "plan i przekrój",
    "nr_inwent": "T.E-09.35",
    "region": null,
    "maxWidth": 818,
    "maxHeight": 1658,
    "fileUpload": null,
    "Authors": null,
    "GraphicsTypes": null
}