{
    "grafika_id": 15021,
    "mime": "image/png",
    "grafika": [],
    "data_wykonania": "/Date(1642287600000)/",
    "dataWykonaniaString": "2022-01-16",
    "grafika_nazwa": "plan",
    "wielkosc": 0,
    "autor_nazwa": "Górny Andrzej",
    "jaskinia_id": 0,
    "jaskinia_nazwa": null,
    "typ_grafiki_id": 2,
    "typ_grafiki_nazwa": "plan",
    "nr_inwent": "J.Olk.I-02b.167",
    "region": null,
    "maxWidth": 2039,
    "maxHeight": 1180,
    "fileUpload": null,
    "Authors": null,
    "GraphicsTypes": null
}